reduct/__init__.py
reduct/bucket.py
reduct/client.py
reduct/error.py
reduct/http.py
reduct/record.py
reduct/time.py
reduct/version.py
reduct/msg/__init__.py
reduct/msg/bucket.py
reduct/msg/replication.py
reduct/msg/server.py
reduct/msg/token.py
reduct_py-1.17.2.dist-info/licenses/LICENSE
reduct_py-1.17.2.dist-info/METADATA
reduct_py-1.17.2.dist-info/WHEEL
reduct_py-1.17.2.dist-info/top_level.txt
reduct_py-1.17.2.dist-info/RECORD
