Metadata-Version: 2.4
Name: reduct-py
Version: 1.17.2
Summary: ReductStore Client SDK for Python
Author: Ciaran Moyne
Author-email: Alexey Timin <atimin@gmail.com>, Anthony Cavin <anthony@reduct.store>
Maintainer-email: Alexey Timin <atimin@gmail.com>
License: MIT License
Project-URL: ReductStore, https://www.reduct.store
Project-URL: Documentation, https://www.reduct.store/docs
Project-URL: Source, https://github.com/reductstore/reduct-py
Project-URL: Changelog, https://github.com/reductstore/reduct-py/blob/main/CHANGELOG.md
Project-URL: Twitter, https://twitter.com/ReductStore
Project-URL: Blog, https://www.reduct.store/blog
Keywords: sdk,reductstore,api client,database,time series database
Classifier: Development Status :: 5 - Production/Stable
Classifier: Programming Language :: Python :: 3 :: Only
Classifier: Framework :: aiohttp
Classifier: Intended Audience :: Information Technology
Classifier: Intended Audience :: Developers
Classifier: Intended Audience :: System Administrators
Classifier: Operating System :: OS Independent
Classifier: Topic :: Database :: Front-Ends
Classifier: License :: OSI Approved :: MIT License
Requires-Python: >=3.9
License-File: LICENSE
Requires-Dist: aiohttp<4,>=3.8
Requires-Dist: pydantic<3,>=2.4
Requires-Dist: deprecation<3,>=2.1
Provides-Extra: test
Requires-Dist: pytest<9.0,>=7.4; extra == "test"
Requires-Dist: pytest-mock~=3.11; extra == "test"
Requires-Dist: pytest-asyncio<2.0,>=0.21; extra == "test"
Requires-Dist: requests~=2.31; extra == "test"
Provides-Extra: lint
Requires-Dist: pylint<4.0,>=2.17; extra == "lint"
Provides-Extra: format
Requires-Dist: black<26.0,>=23.9; extra == "format"
Dynamic: license-file
